[
    {
        "id": 1,
        "title": "O que houve com Sr. Miles?",
        "description": "CONTO, Evento inicial",
        "content": "Sr. Miles desapareceu na noite de...",
        "category": [
            "mistery",
            "drama",
            "suspense"
        ],
        "author": "Chris Redfield",
        "published": true,
        "rating": null
    },
    {
        "id": 2,
        "title": "Telekinesis",
        "description": "i can see the future",
        "content": "ft. SZA, Future",
        "category": [
            "travis",
            "scott",
            "suspense"
        ],
        "author": "James Webb",
        "published": true,
        "rating": null
    }
]